platform_wasm/__init__.py
platform_wasm/matplotlib.py
platform_wasm/panda3d.py
platform_wasm/textual.py
platform_wasm/todo.py
platform_wasm/wcwidth.py
platform_wasm/matplotlib/__init__.py
platform_wasm/matplotlib/pyplot.py
platform_wasm/pygame/__init__.py
platform_wasm/pygame/mixer_music.py
platform_wasm/pygame/timer.py
platform_wasm/pygame/vidcap.py
platform_wasm-0.1.5.dist-info/licenses/LICENSE
platform_wasm-0.1.5.dist-info/METADATA
platform_wasm-0.1.5.dist-info/WHEEL
platform_wasm-0.1.5.dist-info/top_level.txt
platform_wasm-0.1.5.dist-info/zip-safe
platform_wasm-0.1.5.dist-info/RECORD
