Metadata-Version: 2.4
Name: platform_wasm
Version: 0.1.5
Summary: support for interfacing packages with wasm hosts.
Home-page: https://github.com/pygame-web/platform_wasm
Author: Paul Peny
Project-URL: Wiki, https://pygame-web.github.io/platform_wasm/README.md
Project-URL: Bug Tracker, https://github.com/pygame-web/platform_wasm/issues
Project-URL: Source Code, https://github.com/pygame-web/platform_wasm
Project-URL: Project Page, https://github.com/pygame-web/platform_wasm
Classifier: Programming Language :: Python :: 3
Classifier: License :: OSI Approved :: MIT License
Classifier: Operating System :: OS Independent
Classifier: Environment :: WebAssembly
Classifier: Environment :: WebAssembly :: Emscripten
Classifier: Environment :: WebAssembly :: WASI
Requires-Python: >=3.11
License-File: LICENSE
Dynamic: license-file
